teletraffic/__init__.py
teletraffic/libTeletrafficAll.dll
teletraffic/main.py
teletraffic-0.0.1.dist-info/METADATA
teletraffic-0.0.1.dist-info/WHEEL
teletraffic-0.0.1.dist-info/licenses/LICENSE
teletraffic-0.0.1.dist-info/RECORD
