Metadata-Version: 2.4
Name: teletraffic
Version: 0.0.1
Summary: Main teletraffic functions
Project-URL: Homepage, https://example.com
Author-email: Aleksey Hmelevskoy <aleksey.hmelevskoi@gmail.com>
License-Expression: MIT
License-File: LICENSE
Classifier: License :: OSI Approved :: MIT License
Classifier: Operating System :: Microsoft :: Windows
Classifier: Programming Language :: Python :: 3
Requires-Python: >=3.9.7
